yolobel/enums.py
yolobel/processing.py
yolobel/vidbox.py
yolobel/yolobel.py
yolobel-0.0.3.dist-info/METADATA
yolobel-0.0.3.dist-info/WHEEL
yolobel-0.0.3.dist-info/entry_points.txt
yolobel-0.0.3.dist-info/top_level.txt
yolobel-0.0.3.dist-info/RECORD
